happypandax_client/__init__.py
happypandax_client/client.py
happypandax_client/exceptions.py
happypandax_client/tests/__init__.py
happypandax_client-1.0.0.dist-info/LICENSE
happypandax_client-1.0.0.dist-info/METADATA
happypandax_client-1.0.0.dist-info/WHEEL
happypandax_client-1.0.0.dist-info/top_level.txt
happypandax_client-1.0.0.dist-info/zip-safe
happypandax_client-1.0.0.dist-info/RECORD
