Metadata-Version: 2.1
Name: happypandax-client
Version: 1.0.0
Summary: Client library for communicating with HappyPanda X servers
Home-page: https://github.com/happypandax/py-client
Author: Twiddly
Author-email: twiddly@pewpew.com
License: MIT
Platform: UNKNOWN
Classifier: Development Status :: 4 - Beta
Classifier: Environment :: Other Environment
Classifier: Intended Audience :: Developers
Classifier: License :: OSI Approved :: MIT License
Classifier: Operating System :: OS Independent
Classifier: Programming Language :: Python :: 3
Classifier: Topic :: Software Development :: Libraries
